COPYING
README.rst
setup.py
sasco_utils/__init__.py
sasco_utils/datetime.py
sasco_utils/dict.py
sasco_utils.egg-info/PKG-INFO
sasco_utils.egg-info/SOURCES.txt
sasco_utils.egg-info/dependency_links.txt
sasco_utils.egg-info/top_level.txt