Metadata-Version: 1.1
Name: sasco-utils
Version: 0.0.4
Summary: Python module with utils used in SASCO company
Home-page: https://github.com/sascocl/python-sasco-utils
Author: Esteban De La Fuente Rubio, DeLaF
Author-email: esteban@sasco.cl
License: LGPL
Keywords: utils
Platform: UNKNOWN
Classifier: Development Status :: 5 - Production/Stable
Classifier: Intended Audience :: Developers
Classifier: Topic :: Software Development :: Build Tools
Classifier: License :: OSI Approved :: GNU Lesser General Public License v3 or later (LGPLv3+)
Classifier: Programming Language :: Python :: 3
